<?xml version="1.0" encoding="utf-8"?>
<odoo>
    <record id="ir_cron_send_daily_email_dashboard" model="ir.cron">
        <field name="name">Send Daily Email Dashboard</field>
        <field name="interval_number">1</field>
        <field name="interval_type">days</field>
        <field name="numbercall">-1</field>
        <field name="doall" eval="False"/>
        <field name="model_id" ref="model_zafco_email_scheduler"/>
        <field name="code">model._process_send_email()</field>
        <field name="state">code</field>
    </record>
</odoo>